jsonpatchplus/__init__.py
jsonpatchplus/core.py
jsonpatchplus/ctypes.py
jsonpatchplus/exceptions.py
jsonpatchplus/utils.py
jsonpatchplus/loaders/__init__.py
jsonpatchplus/loaders/jsonpatch.py
jsonpatchplus/loaders/jsonpatchplus.py
jsonpatchplus/preprocessors/__init__.py
jsonpatchplus/preprocessors/jsonpath.py
jsonpatchplus-0.2.0.dist-info/LICENSE
jsonpatchplus-0.2.0.dist-info/METADATA
jsonpatchplus-0.2.0.dist-info/WHEEL
jsonpatchplus-0.2.0.dist-info/top_level.txt
jsonpatchplus-0.2.0.dist-info/RECORD
