Metadata-Version: 2.1
Name: jsonpatchplus
Version: 0.2.0
Summary: JsonPatch+
Author-email: Elmer Nocon <elmernocon@gmail.com>
License: MIT License
Requires-Python: >=3.9
License-File: LICENSE
Requires-Dist: jsonpatch
Requires-Dist: jsonpath-ng
Requires-Dist: jsonpointer
Requires-Dist: PyYAML
Provides-Extra: dev
Requires-Dist: black ; extra == 'dev'
Requires-Dist: build ; extra == 'dev'
Requires-Dist: twine ; extra == 'dev'
Provides-Extra: test
Requires-Dist: deepdiff ; extra == 'test'
